pysmarlaconnectapi/__init__.py
pysmarlaconnectapi/classes/__init__.py
pysmarlaconnectapi/classes/auth_token.py
pysmarlaconnectapi/classes/connection.py
pysmarlaconnectapi/connection_hub/__init__.py
pysmarlaconnectapi/federwiege/__init__.py
pysmarlaconnectapi/federwiege/classes/__init__.py
pysmarlaconnectapi/federwiege/classes/property.py
pysmarlaconnectapi/federwiege/classes/service.py
pysmarlaconnectapi/federwiege/services/analyser_service.py
pysmarlaconnectapi/federwiege/services/babywiege_service.py
pysmarlaconnectapi-0.1.0.dist-info/WHEEL
pysmarlaconnectapi-0.1.0.dist-info/METADATA
pysmarlaconnectapi-0.1.0.dist-info/RECORD
