Metadata-Version: 2.3
Name: pysmarlaconnectapi
Version: 0.1.0
Summary: Swing2Sleep Smarla API via websocket with signalr protocol
Author-email: Robin Lintermann <robin.lintermann@explicatis.com>
Requires-Python: >=3.11.9
Classifier: Development Status :: 1 - Planning
Classifier: Programming Language :: Python :: 3 :: Only
Classifier: Programming Language :: Python :: 3.11
Requires-Dist: aiohttp~=3.11.11
Requires-Dist: jsonpickle~=4.0.0
Requires-Dist: pysignalr~=1.1.0
